sisu_wrapper/__init__.py
sisu_wrapper/client.py
sisu_wrapper/exceptions.py
sisu_wrapper/models.py
sisu_wrapper/service.py
sisu_wrapper-0.2.0.dist-info/METADATA
sisu_wrapper-0.2.0.dist-info/WHEEL
sisu_wrapper-0.2.0.dist-info/licenses/LICENSE
sisu_wrapper-0.2.0.dist-info/RECORD
