Metadata-Version: 2.4
Name: sisu-wrapper
Version: 0.2.0
Summary: A lightweight wrapper for the Aalto University Sisu API
Project-URL: Homepage, https://github.com/kctong529/sisukas
Project-URL: Repository, https://github.com/kctong529/sisukas/sisu-wrapper
Project-URL: Issues, https://github.com/kctong529/sisukas/issues
Author-email: Ki Chun Tong <kichun.tong@aalto.fi>
License: MIT
License-File: LICENSE
Requires-Python: >=3.10
Requires-Dist: requests>=2.32.5
Provides-Extra: dev
Requires-Dist: pytest-cov>=4.0; extra == 'dev'
Requires-Dist: pytest>=7.0; extra == 'dev'
